odoo/addons/account_payment_purchase_stock/README.rst
odoo/addons/account_payment_purchase_stock/__init__.py
odoo/addons/account_payment_purchase_stock/__manifest__.py
odoo/addons/account_payment_purchase_stock/i18n/account_payment_purchase_stock.pot
odoo/addons/account_payment_purchase_stock/i18n/ca.po
odoo/addons/account_payment_purchase_stock/i18n/es.po
odoo/addons/account_payment_purchase_stock/i18n/es_AR.po
odoo/addons/account_payment_purchase_stock/i18n/fr.po
odoo/addons/account_payment_purchase_stock/i18n/fr_FR.po
odoo/addons/account_payment_purchase_stock/i18n/it.po
odoo/addons/account_payment_purchase_stock/models/__init__.py
odoo/addons/account_payment_purchase_stock/models/stock_rule.py
odoo/addons/account_payment_purchase_stock/readme/CONTRIBUTORS.md
odoo/addons/account_payment_purchase_stock/readme/DESCRIPTION.md
odoo/addons/account_payment_purchase_stock/readme/INSTALL.md
odoo/addons/account_payment_purchase_stock/readme/USAGE.md
odoo/addons/account_payment_purchase_stock/static/description/icon.png
odoo/addons/account_payment_purchase_stock/static/description/index.html
odoo/addons/account_payment_purchase_stock/tests/__init__.py
odoo/addons/account_payment_purchase_stock/tests/test_account_payment_purchase_stock.py
odoo_addon_account_payment_purchase_stock-18.0.1.0.0.2.dist-info/METADATA
odoo_addon_account_payment_purchase_stock-18.0.1.0.0.2.dist-info/WHEEL
odoo_addon_account_payment_purchase_stock-18.0.1.0.0.2.dist-info/top_level.txt
odoo_addon_account_payment_purchase_stock-18.0.1.0.0.2.dist-info/RECORD
